pickle.py
setup.py
micropython_pickle.egg-info/PKG-INFO
micropython_pickle.egg-info/SOURCES.txt
micropython_pickle.egg-info/dependency_links.txt
micropython_pickle.egg-info/top_level.txt