Metadata-Version: 1.0
Name: micropython-pickle
Version: 0.0.2
Summary: Dummy pickle module for MicroPython
Home-page: https://github.com/micropython/micropython/issues/405
Author: MicroPython Developers
Author-email: micro-python@googlegroups.com
License: MIT
Platform: UNKNOWN
